<?xml version="1.0" encoding="UTF-8" ?>
<gresources>
  <gresource prefix="/dev/mufeed/Wordbook/">
    <file compressed="true">style.css</file>
    <file
            compressed="true"
            preprocess="xml-stripblanks"
            alias="shortcuts-dialog.ui"
        >ui/shortcuts-dialog.ui</file>

    <file
            compressed="true"
            preprocess="xml-stripblanks"
        >ui/settings-window.ui</file>
    <file compressed="true" preprocess="xml-stripblanks">ui/window.ui</file>
  </gresource>
</gresources>
